audiometry_trainer/__init__.py
audiometry_trainer/__main__.py
audiometry_trainer/_version_info.py
audiometry_trainer/acoust_values.py
audiometry_trainer/audio_markers.py
audiometry_trainer/dialog_change_frequencies.py
audiometry_trainer/dialog_edit_preferences.py
audiometry_trainer/dialog_set_value.py
audiometry_trainer/global_parameters.py
audiometry_trainer/hughson_westlake.py
audiometry_trainer/main_window.py
audiometry_trainer/pyqtver.py
audiometry_trainer/pysdt.py
audiometry_trainer/qrc_resources.py
audiometry_trainer/utility_functions.py
audiometry_trainer/window_generate_case.py
audiometry_trainer/case_files/danesh_et_al_2018.csv
audiometry_trainer/case_files/danesh_et_al_2018_info.md
audiometry_trainer/case_files/danesh_et_al_2018_info_fr.md
audiometry_trainer/case_files/hamad_et_al_2002_case_3.csv
audiometry_trainer/case_files/hamad_et_al_2002_case_3_info.md
audiometry_trainer/case_files/hamad_et_al_2002_case_3_info_fr.md
audiometry_trainer/case_files/kramer_and_brown_2019_fig_9-3C.csv
audiometry_trainer/case_files/kramer_and_brown_2019_fig_9-3C_info.md
audiometry_trainer/case_files/kramer_and_brown_2019_fig_9-3C_info_fr.md
audiometry_trainer/case_files/lee_et_al_2021_case_1.csv
audiometry_trainer/case_files/lee_et_al_2021_case_1_info.md
audiometry_trainer/case_files/lee_et_al_2021_case_1_info_fr.md
audiometry_trainer/case_files/manzari_2010.csv
audiometry_trainer/case_files/manzari_2010_info.md
audiometry_trainer/case_files/manzari_2010_info_fr.md
audiometry_trainer/case_files/morse-fortier_et_al_2024_case_A.csv
audiometry_trainer/case_files/morse-fortier_et_al_2024_case_A_info.md
audiometry_trainer/case_files/morse-fortier_et_al_2024_case_A_info_fr.md
audiometry_trainer/case_files/morse-fortier_et_al_2024_case_B.csv
audiometry_trainer/case_files/morse-fortier_et_al_2024_case_B_info.md
audiometry_trainer/case_files/morse-fortier_et_al_2024_case_B_info_fr.md
audiometry_trainer/case_files/morse-fortier_et_al_2024_case_C.csv
audiometry_trainer-0.1.16.dist-info/COPYING.txt
audiometry_trainer-0.1.16.dist-info/METADATA
audiometry_trainer-0.1.16.dist-info/WHEEL
audiometry_trainer-0.1.16.dist-info/entry_points.txt
audiometry_trainer-0.1.16.dist-info/top_level.txt
audiometry_trainer-0.1.16.dist-info/RECORD
