Metadata-Version: 2.1
Name: audiometry_trainer
Version: 0.1.16
Summary: Clinical audiometry simulator
Author-email: Samuele Carcagno <sam.carcagno@gmail.com>
License: GNU GENERAL PUBLIC LICENSE
Project-URL: Homepage, https://gitlab.com/sam81/audiometry_trainer
Project-URL: Bug Tracker, https://gitlab.com/sam81/audiometry_trainer/-/issues
Classifier: Programming Language :: Python :: 3
Classifier: License :: OSI Approved :: GNU General Public License v3 (GPLv3)
Classifier: Operating System :: OS Independent
Classifier: Development Status :: 3 - Alpha
Classifier: Environment :: X11 Applications :: Qt
Classifier: Intended Audience :: Developers
Classifier: Operating System :: MacOS :: MacOS X
Classifier: Operating System :: Microsoft :: Windows
Classifier: Operating System :: POSIX
Classifier: Topic :: Scientific/Engineering
Requires-Python: >=3.7
License-File: COPYING.txt
Requires-Dist: matplotlib >=3.0.0
Requires-Dist: numpy >=1.0.0
Requires-Dist: pandas >=1.0.0
Requires-Dist: PyQt6 >=6.6.0
Requires-Dist: scipy >=1.0.1
Provides-Extra: dev
Requires-Dist: sphinx-rtd-theme >=1.0.0 ; extra == 'dev'
